harl/__init__.py
harl/version.py
harl/Networks/__init__.py
harl/Networks/replaybuffer.py
harl/ppo/__init__.py
harl/ppo/action_type.py
harl/ppo/brain.py
harl/ppo/muscle.py
harl/ppo/network.py
harl/sac/__init__.py
harl/sac/action_type.py
harl/sac/brain.py
harl/sac/extract_actor_pi.py
harl/sac/muscle.py
harl/sac/network.py
palaestrai_agents-3.5.5.dist-info/licenses/LICENSE
palaestrai_agents-3.5.5.dist-info/METADATA
palaestrai_agents-3.5.5.dist-info/WHEEL
palaestrai_agents-3.5.5.dist-info/top_level.txt
palaestrai_agents-3.5.5.dist-info/RECORD
