Metadata-Version: 2.4
Name: palaestrai-agents
Version: 3.5.5
Summary: Implementation of src-algorithms for ARL.
Author: Eric MSP Veith <eric.veith@offis.de>
Author-email: eric.veith@offis.de
License: LGPL
Classifier: Development Status :: 5 - Production/Stable
Classifier: Intended Audience :: Science/Research
Classifier: License :: OSI Approved :: GNU Lesser General Public License v3 (LGPLv3)
Classifier: Natural Language :: English
Classifier: Operating System :: OS Independent
Classifier: Programming Language :: Python
Classifier: Programming Language :: Python :: 3
Classifier: Programming Language :: Python :: 3.10
Classifier: Topic :: Scientific/Engineering
Classifier: Topic :: Scientific/Engineering :: Artificial Intelligence
Requires-Python: >=3.10.0
License-File: LICENSE
Requires-Dist: torch>=2.1.0
Requires-Dist: numpy<2.0,>=1.18.5
Provides-Extra: dev
Requires-Dist: tox>=3.23.0; extra == "dev"
Requires-Dist: robotframework>=4.0.0; extra == "dev"
Requires-Dist: pytest>=6.2.4; extra == "dev"
Requires-Dist: pytest-cov; extra == "dev"
Requires-Dist: coverage; extra == "dev"
Requires-Dist: black==24.1.0; extra == "dev"
Requires-Dist: mypy; extra == "dev"
Requires-Dist: ipython; extra == "dev"
Requires-Dist: plotly; extra == "dev"
Dynamic: author
Dynamic: author-email
Dynamic: classifier
Dynamic: description
Dynamic: license
Dynamic: license-file
Dynamic: provides-extra
Dynamic: requires-dist
Dynamic: requires-python
Dynamic: summary
